vicalerts/__init__.py
vicalerts/cli.py
vicalerts/client.py
vicalerts/constants.py
vicalerts/database.py
vicalerts/models.py
vicalerts/parser.py
vicalerts/poller.py
vicalerts/probe_feed.py
vicalerts-0.3.0.dist-info/METADATA
vicalerts-0.3.0.dist-info/WHEEL
vicalerts-0.3.0.dist-info/entry_points.txt
vicalerts-0.3.0.dist-info/licenses/LICENSE
vicalerts-0.3.0.dist-info/RECORD
